[
  {
    "url": "https://en.wikipedia.org/wiki/Literate_programming",
    "descrip": "Literate programming - Wikipedia",
    "title": "Literate programming - Wikipedia",
    "auth": "Wikipedia contributors",
    "date": 0
  },
  {
    "url": "https://www.worthe-it.co.za/blog/2018-05-28-literate-programming.html",
    "descrip": "Empower your Writing with Emacs Org-Mode",
    "title": "Literate Programming",
    "auth": "Justin Wernick",
    "date": 0
  },
  {
    "url": "https://blog.esciencecenter.nl/literate-programming-in-science-1669094541a7",
    "descrip": "Literate Programming in Science",
    "title": "Literate Programming in Science",
    "auth": "unknown",
    "date": 0
  },
  {
    "url": "https://tug.org/TUGboat/tb13-3/childs.pdf",
    "descrip": "childs.pdf",
    "title": "childs.pdf",
    "auth": "",
    "date": 0
  },
  {
    "url": "https://web.stanford.edu/group/cslipublications/cslipublications/site/0937073806.shtml",
    "descrip": "Author: Donald Knuth, Series: CSLI Publications Lecture Notes, Series Number: 27, Price: $32.50 paperback, $32.50 electronic, Length: 368 pages",
    "title": "Literate Programming",
    "auth": "",
    "date": 0
  },
  {
    "url": "http://www.rigwit.co.uk/papers/literate.html",
    "descrip": "Literate Programming in Forth",
    "title": "Literate Programming in Forth",
    "auth": "",
    "date": 0
  },
  {
    "url": "http://www.literateprogramming.com/",
    "descrip": "Learn about literate programming using the CWEB tool for software development. Download a free CWEB distribution for Microsoft Windows",
    "title": "Literate Programming",
    "auth": "unknown",
    "date": 0
  },
  {
    "url": "http://xml.coverpages.org/relaxng-is20021212.pdf",
    "descrip": "relaxng-is20021212.pdf",
    "title": "relaxng-is20021212.pdf",
    "auth": "",
    "date": 0
  },
  {
    "url": "https://github.com/cdosborn/lit",
    "descrip": "A modern tool for literate programming. Contribute to cdosborn/lit development by creating an account on GitHub.",
    "title": "GitHub - cdosborn/lit: A modern tool for literate programming",
    "auth": "cdosborn",
    "date": 0
  },
  {
    "url": "https://github.com/fsprojects/FSharp.Formatting",
    "descrip": "F# tools for generating documentation (Markdown processor and F# code formatter) - fsprojects/FSharp.Formatting",
    "title": "GitHub - fsprojects/FSharp.Formatting: F# tools for generating documentation (Markdown processor and F# code formatter)",
    "auth": "fsprojects",
    "date": 0
  },
  {
    "url": "https://bookdown.org/kochiuyu/Technical-Analysis-with-R/sweave-r-code-in-latex.html",
    "descrip": "This is an introductory textbook that focuses on how to use R to do technical analysis.",
    "title": "9.1 Sweave: R code in LaTex | Techincal Analysis with R",
    "auth": "Ko Chiu Yu",
    "date": 0
  },
  {
    "url": "https://github.com/SciViews/svSweave",
    "descrip": "svSweave - Sweave, Knitr and R Markdown Companion Functions - SciViews/svSweave",
    "title": "GitHub - SciViews/svSweave: svSweave - Sweave, Knitr and R Markdown Companion Functions",
    "auth": "SciViews",
    "date": 0
  }
]