[
  {
    "url": "https://en.wikipedia.org/wiki/PHAR_%28file_format%29",
    "desc": "PHAR (file format) - Wikipedia",
    "title": "PHAR (file format) - Wikipedia",
    "auth": "Wikipedia contributors",
    "date": 0
  },
  {
    "url": "https://php.net/manual/en/wrappers.phar.php",
    "desc": "wrappers.phar.php",
    "title": "wrappers.phar.php",
    "auth": "unknown",
    "date": 0
  },
  {
    "url": "https://php.net/manual/en/class.phar.php",
    "desc": "class.phar.php",
    "title": "class.phar.php",
    "auth": "unknown",
    "date": 0
  },
  {
    "url": "https://php.net/manual/en/phar.buildfromiterator.php",
    "desc": "phar.buildfromiterator.php",
    "title": "phar.buildfromiterator.php",
    "auth": "unknown",
    "date": 0
  },
  {
    "url": "https://php.net/manual/en/phar.createdefaultstub.php",
    "desc": "phar.createdefaultstub.php",
    "title": "phar.createdefaultstub.php",
    "auth": "unknown",
    "date": 0
  },
  {
    "url": "https://stackoverflow.com/questions/11082337/how-to-make-an-executable-phar#11082338",
    "desc": "php - How to make an executable phar? - Stack Overflow",
    "title": "php - How to make an executable phar? - Stack Overflow",
    "auth": "No author for Q&amp;A sites",
    "date": 0
  },
  {
    "url": "https://stackoverflow.com/questions/15750913/generating-a-phar-for-a-simple-application",
    "desc": "php - Generating a PHAR for a simple application - Stack Overflow",
    "title": "php - Generating a PHAR for a simple application - Stack Overflow",
    "auth": "No author for Q&amp;A sites",
    "date": 0
  },
  {
    "url": "https://stackoverflow.com/questions/38214154/how-do-i-correctly-create-and-then-require-a-phar-file",
    "desc": "php - How do I correctly create, and then require a PHAR file? - Stack Overflow",
    "title": "php - How do I correctly create, and then require a PHAR file? - Stack Overflow",
    "auth": "No author for Q&amp;A sites",
    "date": 0
  },
  {
    "url": "https://secure.php.net/manual/en/phar.compress.php",
    "desc": "phar.compress.php",
    "title": "phar.compress.php",
    "auth": "unknown",
    "date": 0
  },
  {
    "url": "https://secure.php.net/manual/en/phar.webphar.php",
    "desc": "phar.webphar.php",
    "title": "phar.webphar.php",
    "auth": "unknown",
    "date": 0
  },
  {
    "url": "https://packagist.org/packages/macfja/phar-builder",
    "desc": "macfja/phar-builder - Packagist",
    "title": "macfja/phar-builder - Packagist",
    "auth": "Jordi Boggiano",
    "date": 0
  },
  {
    "url": "https://www.phptesting.org/",
    "desc": "HTTP_ERROR, Error: Couldn't resolve host name",
    "title": "HTTP_ERROR, Error: Couldn't resolve host name",
    "auth": "unknown",
    "date": 0
  },
  {
    "url": "https://www.phptesting.org/wiki/Phar-Plugin",
    "desc": "HTTP_ERROR, Error: Couldn't resolve host name",
    "title": "HTTP_ERROR, Error: Couldn't resolve host name",
    "auth": "unknown",
    "date": 0
  }
]